README.rst
setup.py
pygfapi/__init__.py
pygfapi/client.py
pygfapi.egg-info/PKG-INFO
pygfapi.egg-info/SOURCES.txt
pygfapi.egg-info/dependency_links.txt
pygfapi.egg-info/requires.txt
pygfapi.egg-info/top_level.txt